falcon_openapi/__init__.py
falcon_openapi/router.py
falcon_openapi-0.5.1.dist-info/LICENSE
falcon_openapi-0.5.1.dist-info/METADATA
falcon_openapi-0.5.1.dist-info/WHEEL
falcon_openapi-0.5.1.dist-info/top_level.txt
falcon_openapi-0.5.1.dist-info/RECORD
