Metadata-Version: 2.1
Name: falcon-openapi
Version: 0.5.1
Summary: Falcon router to map openapi spec to resources
Home-page: https://github.com/StoicPerlman/falcon-openapi/
Author: Sam Kleiner
Author-email: sam@skleiner.com
License: MIT
Keywords: falcon,openapi,api
Platform: UNKNOWN
Requires-Python: >3.5.0
Requires-Dist: falcon
Requires-Dist: pyyaml
